quantities/__init__.py
quantities/_version.py
quantities/decorators.py
quantities/dimensionality.py
quantities/dimensionality.pyi
quantities/markup.py
quantities/quantity.py
quantities/quantity.pyi
quantities/registry.py
quantities/registry.pyi
quantities/umath.py
quantities/uncertainquantity.py
quantities/unitquantity.py
quantities/unitquantity.pyi
quantities/constants/NIST_codata.txt
quantities/constants/__init__.py
quantities/constants/_codata.py
quantities/constants/_utils.py
quantities/constants/alpha.py
quantities/constants/astronomy.py
quantities/constants/atomicunits.py
quantities/constants/deuteron.py
quantities/constants/electromagnetism.py
quantities/constants/electron.py
quantities/constants/helion.py
quantities/constants/mathematical.py
quantities/constants/muon.py
quantities/constants/naturalunits.py
quantities/constants/neutron.py
quantities/constants/proton.py
quantities/constants/quantum.py
quantities/constants/relationships.py
quantities/constants/statisticalmechanics.py
quantities/constants/tau.py
quantities/constants/triton.py
quantities/constants/weak.py
quantities/constants/xray.py
quantities/tests/__init__.py
quantities/tests/common.py
quantities/tests/test_arithmetic.py
quantities/tests/test_comparison.py
quantities/tests/test_constants.py
quantities/tests/test_conversion.py
quantities/tests/test_dimensionality.py
quantities/tests/test_formatting.py
quantities/tests/test_methods.py
quantities/tests/test_persistence.py
quantities/tests/test_umath.py
quantities/tests/test_uncertainty.py
quantities/tests/test_units.py
quantities/typing/__init__.py
quantities/typing/quantities.pyi
quantities/units/__init__.py
quantities/units/acceleration.py
quantities/units/acceleration.pyi
quantities/units/angle.py
quantities/units/angle.pyi
quantities/units/area.py
quantities/units/area.pyi
quantities/units/compound.py
quantities/units/compound.pyi
quantities/units/concentration.py
quantities/units/concentration.pyi
quantities/units/dimensionless.py
quantities-0.16.3.dist-info/licenses/doc/user/license.rst
quantities-0.16.3.dist-info/METADATA
quantities-0.16.3.dist-info/WHEEL
quantities-0.16.3.dist-info/top_level.txt
quantities-0.16.3.dist-info/RECORD
