Metadata-Version: 2.4
Name: quantities
Version: 0.16.3
Summary: Support for physical quantities with units, based on numpy
Author-email: Darren Dale <dsdale24@gmail.com>
Maintainer-email: Andrew Davison <andrew.davison@cnrs.fr>
Project-URL: documentation, http://python-quantities.readthedocs.io/
Project-URL: repository, https://github.com/python-quantities/python-quantities
Project-URL: changelog, https://github.com/python-quantities/python-quantities/blob/master/CHANGES.txt
Project-URL: download, http://pypi.python.org/pypi/quantities
Keywords: quantities,units,physical,constants
Classifier: Development Status :: 4 - Beta
Classifier: Environment :: Console
Classifier: Intended Audience :: Developers
Classifier: Intended Audience :: Education
Classifier: Intended Audience :: End Users/Desktop
Classifier: Intended Audience :: Science/Research
Classifier: Operating System :: OS Independent
Classifier: Programming Language :: Python
Classifier: Topic :: Education
Classifier: Topic :: Scientific/Engineering
Requires-Python: >=3.10
License-File: doc/user/license.rst
Requires-Dist: numpy>=1.24
Provides-Extra: test
Requires-Dist: pytest; extra == "test"
Requires-Dist: wheel; extra == "test"
Provides-Extra: doc
Requires-Dist: sphinx; extra == "doc"
Provides-Extra: scipy
Requires-Dist: scipy; extra == "scipy"
Dynamic: license-file
